ovos_solver_aiml_plugin/__init__.py
ovos_solver_aiml_plugin/version.py
ovos_solver_aiml_plugin-0.0.1.dist-info/LICENSE
ovos_solver_aiml_plugin-0.0.1.dist-info/METADATA
ovos_solver_aiml_plugin-0.0.1.dist-info/WHEEL
ovos_solver_aiml_plugin-0.0.1.dist-info/entry_points.txt
ovos_solver_aiml_plugin-0.0.1.dist-info/top_level.txt
ovos_solver_aiml_plugin-0.0.1.dist-info/zip-safe
ovos_solver_aiml_plugin-0.0.1.dist-info/RECORD
